yimi_mcp_server/__init__.py
yimi_mcp_server-3.0.0.dist-info/METADATA
yimi_mcp_server-3.0.0.dist-info/WHEEL
yimi_mcp_server-3.0.0.dist-info/entry_points.txt
yimi_mcp_server-3.0.0.dist-info/RECORD
