Metadata-Version: 2.4
Name: yimi-mcp-server
Version: 3.0.0
Summary: Add your description here
Author-email: shs <shang.n@163.com>
Requires-Python: >=3.10
Requires-Dist: mcp[cli]>=1.9.3
Requires-Dist: requests
